nuedit/__init__.py
NuEdit-0.0.1.dist-info/LICENSE
NuEdit-0.0.1.dist-info/METADATA
NuEdit-0.0.1.dist-info/WHEEL
NuEdit-0.0.1.dist-info/top_level.txt
NuEdit-0.0.1.dist-info/RECORD
